Verilog/Half Adder/Half_Adder.v
`timescale 1ns/10ps
module Half_Adder (Sum,Carry,A,B);

input A,B;
output Sum,Carry;

and inst1(Carry,A,B);
xor inst2(Sum,A,B);

endmodule

Verilog/Full Adder/Full_Adder.v
`timescale 1ns/10ps
`include "Half_Adder.v"

module Full_Adder (Sum,Carry,A,B,CI);

input A,B,CI;
output Sum,Carry;
wire x1,x2,x3;

Half_Adder inst1(x1,x2,A,B);
Half_Adder inst2(Sum,x3,CI,x1);
or inst3(Carry,x2,x3);

endmodule

Verilog/Full Adder/Full_Adder_tb.v
`timescale 1ns/10ps

module Full_Adder_tb;

reg A,B,CI;
wire Sum,Carry;


Full_Adder UUT (Sum,Carry,A,B,CI);

initial
    begin
        $dumpfile("Full_Adder_tb.vcd");
        $dumpvars(0,Full_Adder_tb);

        A=0;
        B=0;
        CI=0;
    end

initial
    begin
        
        #10
        A = 0;
        B = 1;
        CI=0;

        #10
        A = 1;
        B = 0;
        CI=0;

        #10
        A = 1;
        B = 1;
        CI=0;
        
        #10
        A=0;
        B=0;
        CI=1;

        #10
        A=0;
        B=1;
        CI=1;

        #10
        A=1;
        B=0;
        CI=1;

        #10
        A=1;
        B=1;
        CI=1;

        #10
        A=1;
        B=1;
        CI=1;

    end

always @(Sum,Carry)
$display("time =%0t \t A =%b, B =%b, CI =%b, Sum =%b and Carry =%b",$time,A,B,CI,Sum,Carry);

endmodule

Verilog/Full Adder/Full_Adder_tb.vcd
$date
	Sat Nov 12 02:58:40 2022
$end
$version
	Icarus Verilog
$end
$timescale
	10ps
$end
$scope module Full_Adder_tb $end
$var wire 1 ! Sum $end
$var wire 1 " Carry $end
$var reg 1 # A $end
$var reg 1 $ B $end
$var reg 1 % CI $end
$scope module UUT $end
$var wire 1 # A $end
$var wire 1 $ B $end
$var wire 1 % CI $end
$var wire 1 " Carry $end
$var wire 1 & x3 $end
$var wire 1 ' x2 $end
$var wire 1 ( x1 $end
$var wire 1 ! Sum $end
$scope module inst1 $end
$var wire 1 # A $end
$var wire 1 $ B $end
$var wire 1 ' Carry $end
$var wire 1 ( Sum $end
$upscope $end
$scope module inst2 $end
$var wire 1 % A $end
$var wire 1 ( B $end
$var wire 1 & Carry $end
$var wire 1 ! Sum $end
$upscope $end
$upscope $end
$upscope $end
$enddefinitions $end
#0
$dumpvars
0(
0'
0&
0%
0$
0#
0"
0!
$end
#1000
1!
1(
1$
#2000
0$
1#
#3000
1"
0!
1'
0(
1$
#4000
0"
1!
0'
1%
0$
0#
#5000
1"
1&
0!
1(
1$
#6000
0$
1#
#7000
0&
1!
1'
0(
1$
